odoo8_addon_mgmtsystem_nonconformity_analytic-8.0.1.0.0.99.dev5-py2.7-nspkg.pth
odoo8_addon_mgmtsystem_nonconformity_analytic-8.0.1.0.0.99.dev5.dist-info/DESCRIPTION.rst
odoo8_addon_mgmtsystem_nonconformity_analytic-8.0.1.0.0.99.dev5.dist-info/METADATA
odoo8_addon_mgmtsystem_nonconformity_analytic-8.0.1.0.0.99.dev5.dist-info/RECORD
odoo8_addon_mgmtsystem_nonconformity_analytic-8.0.1.0.0.99.dev5.dist-info/WHEEL
odoo8_addon_mgmtsystem_nonconformity_analytic-8.0.1.0.0.99.dev5.dist-info/metadata.json
odoo8_addon_mgmtsystem_nonconformity_analytic-8.0.1.0.0.99.dev5.dist-info/namespace_packages.txt
odoo8_addon_mgmtsystem_nonconformity_analytic-8.0.1.0.0.99.dev5.dist-info/top_level.txt
odoo_addons/mgmtsystem_nonconformity_analytic/README.rst
odoo_addons/mgmtsystem_nonconformity_analytic/__init__.py
odoo_addons/mgmtsystem_nonconformity_analytic/__openerp__.py
odoo_addons/mgmtsystem_nonconformity_analytic/i18n/de.po
odoo_addons/mgmtsystem_nonconformity_analytic/i18n/es.po
odoo_addons/mgmtsystem_nonconformity_analytic/i18n/hr.po
odoo_addons/mgmtsystem_nonconformity_analytic/i18n/mgmtsystem_nonconformity_analytic.pot
odoo_addons/mgmtsystem_nonconformity_analytic/i18n/pt.po
odoo_addons/mgmtsystem_nonconformity_analytic/i18n/sl.po
odoo_addons/mgmtsystem_nonconformity_analytic/models/__init__.py
odoo_addons/mgmtsystem_nonconformity_analytic/models/mgmtsystem_nonconformity.py
odoo_addons/mgmtsystem_nonconformity_analytic/static/description/icon.png
odoo_addons/mgmtsystem_nonconformity_analytic/views/mgmtsystem_nonconformity.xml
